LICENSE
MANIFEST.in
README.rst
setup.cfg
setup.py
sphinxcontrib/__init__.py
sphinxcontrib/textstyle/__init__.py
sphinxcontrib/textstyle/color.py
sphinxcontrib/textstyle/column.py
sphinxcontrib/textstyle/deleted.py
sphinxcontrib/textstyle/ruby.py
sphinxcontrib_textstyle.egg-info/PKG-INFO
sphinxcontrib_textstyle.egg-info/SOURCES.txt
sphinxcontrib_textstyle.egg-info/dependency_links.txt
sphinxcontrib_textstyle.egg-info/namespace_packages.txt
sphinxcontrib_textstyle.egg-info/not-zip-safe
sphinxcontrib_textstyle.egg-info/requires.txt
sphinxcontrib_textstyle.egg-info/top_level.txt