Metadata-Version: 1.1
Name: sphinxcontrib-textstyle
Version: 0.2.3
Summary: Sphinx "textstyle" extension
Home-page: http://bitbucket.org/r_rudi/sphinxcontrib-textstyle
Author: WAKAYAMA Shirou
Author-email: shirou.faw@gmail.com
License: BSD
Download-URL: http://pypi.python.org/pypi/sphinxcontrib-textstyle
Platform: any
Classifier: Development Status :: 4 - Beta
Classifier: Environment :: Console
Classifier: Environment :: Web Environment
Classifier: Intended Audience :: Developers
Classifier: License :: OSI Approved :: BSD License
Classifier: Operating System :: OS Independent
Classifier: Programming Language :: Python
Classifier: Topic :: Documentation
Classifier: Topic :: Utilities
